send_qq_email/__init__.py
send_qq_email-0.1.0.dist-info/METADATA
send_qq_email-0.1.0.dist-info/WHEEL
send_qq_email-0.1.0.dist-info/entry_points.txt
send_qq_email-0.1.0.dist-info/RECORD
