Metadata-Version: 2.4
Name: send-qq-email
Version: 0.1.0
Summary: Add your description here
Requires-Python: >=3.13
Requires-Dist: mcp[cli]>=1.11.0
